opensea_sdk/__init__.py
opensea_sdk/opensea_stream.py
opensea_sdk/utils.py
opensea_stream-0.1.0.dist-info/LICENSE
opensea_stream-0.1.0.dist-info/METADATA
opensea_stream-0.1.0.dist-info/WHEEL
opensea_stream-0.1.0.dist-info/top_level.txt
opensea_stream-0.1.0.dist-info/RECORD
